[
  {
    "name": "Rasha Ali",
    "userName": ""
  },
  {
    "name": "Feruz Teame",
    "userName": ""
  },
  {
    "name": "Ayse Akyol",
    "userName": ""
  },
  {
    "name": "Kateryna Boichuk",
    "userName": ""
  },
  {
    "name": "Gülcan Nuralp",
    "userName": ""
  },
  {
    "name": "Beyhan Yediyildiz",
    "userName": ""
  },
  {
    "name": "Abdulrssak Abdi",
    "userName": ""
  },
  {
    "name": "Omer Sancak",
    "userName": ""
  },
  {
    "name": "Mahmoud Hasan",
    "userName": ""
  },
  {
    "name": "Saleh Hasan",
    "userName": ""
  },
  {
    "name": "Thomas Gebrehiwet",
    "userName": ""
  },
  {
    "name": "Mesud Varol",
    "userName": ""
  },
  {
    "name": "Luis Montilla",
    "userName": ""
  },
  {
    "name": "Adalrazaq Altaih",
    "userName": ""
  },
  {
    "name": "Abed Amir",
    "userName": ""
  },
]
